interpretablefa/__init__.py
interpretablefa/interpretablefa.py
interpretablefa-5.1.0.dist-info/LICENSE.txt
interpretablefa-5.1.0.dist-info/METADATA
interpretablefa-5.1.0.dist-info/WHEEL
interpretablefa-5.1.0.dist-info/top_level.txt
interpretablefa-5.1.0.dist-info/RECORD
