Metadata-Version: 2.1
Name: interpretablefa
Version: 5.1.0
Summary: A package for interpretable factor analysis
Author: Justin Philip Tuazon, Gia Mizrane Abubo
License: GNU General Public License 3.0
Classifier: Intended Audience :: Science/Research
Classifier: Intended Audience :: Developers
Classifier: Programming Language :: Python
Classifier: Topic :: Scientific/Engineering
Requires-Python: >=3.8
License-File: LICENSE.txt
Requires-Dist: tensorflow-hub
Requires-Dist: numpy
Requires-Dist: pandas
Requires-Dist: scikit-learn
Requires-Dist: scipy
Requires-Dist: factor-analyzer
Requires-Dist: seaborn
Requires-Dist: matplotlib
Requires-Dist: statsmodels
